mcp_ccmonet/__init__.py
mcp_ccmonet/ccmonet_server/__init__.py
mcp_ccmonet/ccmonet_server/config.py
mcp_ccmonet/ccmonet_server/server.py
mcp_ccmonet/main.py
mcp_ccmonet-0.1.0.dist-info/LICENSE
mcp_ccmonet-0.1.0.dist-info/METADATA
mcp_ccmonet-0.1.0.dist-info/WHEEL
mcp_ccmonet-0.1.0.dist-info/entry_points.txt
mcp_ccmonet-0.1.0.dist-info/RECORD
