Metadata-Version: 2.3
Name: mcp-ccmonet
Version: 0.1.0
Summary: ccMonet MCP server for forwarding messages from clients like Claude to ccMonet API
License: MIT
Keywords: mcp,claude,ccMonet,ai
Author: ccMonet
Author-email: development@platoxai.com
Requires-Python: >=3.11,<4.0
Classifier: Development Status :: 4 - Beta
Classifier: Intended Audience :: Developers
Classifier: License :: OSI Approved :: MIT License
Classifier: Operating System :: OS Independent
Classifier: Programming Language :: Python :: 3
Classifier: Programming Language :: Python :: 3.11
Classifier: Programming Language :: Python :: 3.12
Classifier: Programming Language :: Python :: 3.13
Requires-Dist: httpx[socks] (>=0.28.1,<0.29.0)
Requires-Dist: mcp[cli] (>=1.6.0,<2.0.0)
Project-URL: Homepage, https://www.ccmonet.ai
Project-URL: Repository, https://github.com/PlatoX-Type/mcp_ccmonet
